{"generated": "2026-05-24", "analysis_period": {"start": "2016-01-02", "end": "2026-05-23", "label": "2016-01-02 to 2026-05-23"}, "games": {"superlotto_plus": {"game": "superlotto_plus", "name": "SuperLotto Plus", "main_range": [1, 47], "main_count": 5, "bonus_range": [1, 27], "draw_count": 1085, "oldest": "2016-01-02", "newest": "2026-05-23", "source": "https://www.lotto.net (year archives)", "main_freq": [0, 134, 118, 126, 132, 100, 127, 124, 150, 109, 133, 114, 120, 125, 116, 106, 128, 110, 104, 104, 119, 124, 124, 96, 111, 112, 89, 124, 107, 91, 116, 97, 112, 120, 115, 107, 111, 118, 124, 130, 103, 101, 123, 116, 122, 108, 120, 105], "bonus_freq": [0, 42, 42, 58, 46, 40, 44, 37, 36, 42, 36, 37, 47, 32, 27, 45, 39, 44, 40, 41, 39, 31, 44, 39, 51, 36, 37, 33], "full_data_oldest": "2016-01-02", "full_data_newest": "2026-05-23", "full_data_count": 1085}, "fantasy5": {"game": "fantasy5", "name": "Fantasy5", "main_range": [1, 39], "main_count": 5, "bonus_range": null, "draw_count": 231, "oldest": "2025-10-05", "newest": "2026-05-23", "source": "drawanalytics.com (supplement)", "main_freq": [0, 30, 30, 24, 28, 28, 25, 27, 31, 31, 41, 32, 22, 38, 41, 23, 33, 31, 37, 32, 35, 29, 19, 29, 26, 25, 29, 25, 37, 28, 26, 31, 33, 41, 21, 34, 24, 25, 26, 28], "bonus_freq": null, "full_data_oldest": "2025-10-05", "full_data_newest": "2026-05-23", "full_data_count": 231}, "powerball": {"game": "powerball", "name": "Powerball", "main_range": [1, 69], "main_count": 5, "bonus_range": [1, 26], "draw_count": 1333, "oldest": "2016-01-02", "newest": "2026-05-23", "source": "https://www.lotto.net (year archives)", "main_freq": [0, 92, 94, 106, 92, 88, 103, 92, 92, 89, 89, 98, 99, 72, 84, 92, 100, 92, 100, 99, 95, 120, 89, 116, 97, 84, 77, 112, 117, 86, 94, 95, 110, 114, 83, 90, 113, 107, 88, 107, 96, 87, 92, 96, 103, 97, 79, 106, 84, 78, 93, 89, 106, 107, 93, 84, 94, 91, 91, 103, 90, 121, 108, 112, 115, 86, 97, 98, 92, 110], "bonus_freq": [0, 55, 50, 53, 64, 57, 49, 44, 45, 53, 45, 46, 45, 48, 62, 44, 39, 42, 59, 49, 57, 61, 44, 49, 62, 57, 54], "full_data_oldest": "2016-01-02", "full_data_newest": "2026-05-23", "full_data_count": 1333}, "mega_millions": {"game": "mega_millions", "name": "Mega Millions", "main_range": [1, 70], "main_count": 5, "bonus_range": [1, 25], "draw_count": 1024, "oldest": "2016-01-05", "newest": "2026-05-22", "source": "https://www.lotto.net (year archives)", "main_freq": [0, 70, 70, 84, 74, 61, 74, 69, 80, 61, 88, 83, 67, 73, 84, 74, 74, 89, 80, 77, 82, 70, 76, 59, 82, 69, 77, 73, 76, 76, 79, 96, 66, 87, 76, 62, 63, 72, 86, 73, 78, 72, 86, 82, 74, 63, 81, 64, 73, 70, 61, 56, 73, 72, 71, 62, 75, 69, 83, 72, 62, 70, 72, 68, 78, 57, 82, 57, 66, 71, 68], "bonus_freq": [0, 47, 41, 44, 46, 32, 45, 44, 34, 51, 45, 51, 42, 46, 42, 39, 36, 37, 44, 39, 31, 31, 46, 28, 47, 36], "full_data_oldest": "2016-01-01", "full_data_newest": "2026-05-22", "full_data_count": 1085}}}